mcp_agent_db/__init__.py
mcp_agent_db/agente_inteligente_v2.py
mcp_agent_db/cache_manager.py
mcp_agent_db/consulta_tool.py
mcp_agent_db/conversation_memory.py
mcp_agent_db/executores.py
mcp_agent_db/filtros_empresa.py
mcp_agent_db/gerar_schema.py
mcp_agent_db/main.py
mcp_agent_db/mcp_servers.py
mcp_agent_db/prompt_sql.py
mcp_agent_db/scheduler.py
mcp_agent_db/schema_loader.py
mcp_agent_db/settings.py
mcp_agent_db/sql_generator.py
mcp_agent_db/teste_filtros_corrigidos.py
mcp_agent_db/schemas/casaa.json
mcp_agent_db/static/logo.png
mcp_agent_db/templates/index.html
mcp_agent_db-1.0.8.dist-info/licenses/LICENSE
mcp_agent_db-1.0.8.dist-info/METADATA
mcp_agent_db-1.0.8.dist-info/WHEEL
mcp_agent_db-1.0.8.dist-info/entry_points.txt
mcp_agent_db-1.0.8.dist-info/top_level.txt
mcp_agent_db-1.0.8.dist-info/RECORD
